setup.py
bin/fuuniest-joke
fuuniest/__init__.py
fuuniest.egg-info/PKG-INFO
fuuniest.egg-info/SOURCES.txt
fuuniest.egg-info/dependency_links.txt
fuuniest.egg-info/not-zip-safe
fuuniest.egg-info/requires.txt
fuuniest.egg-info/top_level.txt