Metadata-Version: 1.0
Name: fuuniest
Version: 0.1
Summary: The fuuniest joke in the world
Home-page: UNKNOWN
Author: Flying Circus
Author-email: flyingcircus@example.com
License: MIT
Platform: UNKNOWN
